ultratenant/__init__.py
ultratenant/middlewares.py
ultratenant/models.py
ultratenant/multidb.py
ultratenant/singledb.py
ultratenant/threadlocal.py
django_ultratenant-0.0.3.dist-info/LICENSE
django_ultratenant-0.0.3.dist-info/WHEEL
django_ultratenant-0.0.3.dist-info/METADATA
django_ultratenant-0.0.3.dist-info/RECORD
