Metadata-Version: 2.1
Name: django-ultratenant
Version: 0.0.3
Summary: One django library to rule all multi-tenant.
Keywords: ultratenant,django,tenant id,multi-database,multi-tenant,multi-schema,postgres
Author-email: Lucas Cezimbra <lucas@cezimbra.tec.br>
Maintainer: HBNetwork
Requires-Python: >=3.7
Classifier: Development Status :: 2 - Pre-Alpha
Classifier: Intended Audience :: Developers
Classifier: License :: OSI Approved :: MIT License
Classifier: Natural Language :: English
Classifier: Programming Language :: Python :: 3
Classifier: Programming Language :: Python :: 3.6
Classifier: Programming Language :: Python :: 3.7
Classifier: Programming Language :: Python :: 3.8
Classifier: Framework :: Django
Classifier: Framework :: Django :: 3
Classifier: Framework :: Django :: 3.2
Requires-Dist: django>=3.2.7
Requires-Dist: dj-database-url==1.0.0
Requires-Dist: flit>=3.4 ; extra == "build"
Requires-Dist: coverage ; extra == "test"
Requires-Dist: coveralls ; extra == "test"
Requires-Dist: flake8 ; extra == "test"
Requires-Dist: pre-commit ; extra == "test"
Requires-Dist: pytest ; extra == "test"
Requires-Dist: pytest-cov ; extra == "test"
Requires-Dist: pytest-django ; extra == "test"
Requires-Dist: pytest-mock ; extra == "test"
Requires-Dist: python-decouple ; extra == "test"
Requires-Dist: tox ; extra == "test"
Project-URL: documentation, https://github.com/HBN3tw0rk/django-ultratenant/README.md
Project-URL: repository, https://github.com/HBN3tw0rk/django-ultratenant
Provides-Extra: build
Provides-Extra: test
